ipeanim/__init__.py
ipeanim-0.3.0.data/scripts/ipeanim
ipeanim-0.3.0.dist-info/AUTHORS
ipeanim-0.3.0.dist-info/LICENSE
ipeanim-0.3.0.dist-info/METADATA
ipeanim-0.3.0.dist-info/WHEEL
ipeanim-0.3.0.dist-info/pbr.json
ipeanim-0.3.0.dist-info/top_level.txt
ipeanim-0.3.0.dist-info/RECORD
