Metadata-Version: 2.1
Name: ipeanim
Version: 0.3.0
Summary: This package demonstrates building and publishing Python Packages with GitHubs infrastructure
Home-page: UNKNOWN
Author: Sören Wegener
Author-email: wegener92@gmail.com
License: UNKNOWN
Project-URL: Source Code, https://github.com/soerface/ipeanim
Project-URL: Bug Tracker, https://github.com/soerface/ipeanim/issues
Project-URL: Documentation, https://github.com/soerface/ipeanim/blob/master/README.md
Platform: UNKNOWN
Requires-Dist: pbr (==5.4.4)
